dqp/__init__.py
dqp/dQP.py
dqp/lin_solvers.py
dqp/qp_diagnostic.py
dqp/set_solver_tolerance.py
dqp/sparse_helper.py
dqp/unit_test.py
libdqp-0.1.1.dist-info/METADATA
libdqp-0.1.1.dist-info/WHEEL
libdqp-0.1.1.dist-info/top_level.txt
libdqp-0.1.1.dist-info/RECORD
