Metadata-Version: 2.4
Name: libdqp
Version: 0.1.1
Summary: Differentiation Through Black-Box Quadratic Programming Solvers
Author: Connor W. Magoon, Fengyu Yang, Noam Aigerman, Shahar Z. Kovalsky
License: MIT
Project-URL: Homepage, https://github.com/cwmagoon/dQP
Project-URL: Paper, https://arxiv.org/pdf/2410.06324
Keywords: quadratic programming,differentiation,optimization,pytorch,machine learning
Classifier: License :: OSI Approved :: MIT License
Classifier: Programming Language :: Python :: 3
Classifier: Programming Language :: Python :: 3.9
Classifier: Programming Language :: Python :: 3.10
Classifier: Programming Language :: Python :: 3.11
Classifier: Programming Language :: Python :: 3.12
Classifier: Programming Language :: Python :: 3.13
Classifier: Programming Language :: Python :: 3.14
Requires-Python: >=3.9
Requires-Dist: torch>=2.0.0
Requires-Dist: numpy
Requires-Dist: scipy
Requires-Dist: qpsolvers
Requires-Dist: joblib
Requires-Dist: clarabel
Requires-Dist: cvxopt
Requires-Dist: daqp
Requires-Dist: ecos
Requires-Dist: gurobipy
Requires-Dist: highspy
Requires-Dist: mosek
Requires-Dist: osqp
Requires-Dist: piqp
Requires-Dist: proxsuite
Requires-Dist: qpalm
Requires-Dist: quadprog
Requires-Dist: scs
Requires-Dist: pypardiso
Requires-Dist: qdldl
Dynamic: requires-python
